[
    {
        "id": 1,
        "name": "Javascript",
        "img": "https://i.ibb.co/19B9X65/Java-Script.png",
        "experience": "Experties"
    },
    {
        "id": 2,
        "name": "React.js",
        "img": "https://i.ibb.co/1rmWk5b/react.png",
        "experience": "Experties"
    },
    {
        "id": 3,
        "name": "TailwindCSS",
        "img": "https://i.ibb.co/StjjgDt/tailwind.jpg",
        "experience": "Experties"
    },
    {
        "id": 3,
        "name": "Bootraps",
        "img": "https://i.ibb.co/7WjXrZT/boostrap.png",
        "experience": "Experties"
    },
    {
        "id": 1,
        "name": "Node",
        "img": "https://i.ibb.co/BnRB26s/node.png",
        "experience": "Comfotable"
    },
    {
        "id": 2,
        "name": "Express",
        "img": "https://i.ibb.co/d44pp45/express.png",
        "experience": "Comfotable"
    },
    {
        "id": 3,
        "name": "HTML",
        "img": "https://i.ibb.co/WKFqmhb/html.png",
        "experience": "Experties"
    },
    {
        "id": 3,
        "name": "CSS",
        "img": "https://i.ibb.co/vYnzsbY/css.png",
        "experience": "Experties"
    }
]
